{
    "nodes": [
        {
            "id": "internet",
            "label": "Internet",
            "x": 0,
            "y": 0,
            "width": 240,
            "height": 40,
            "bgColor": "#ffee55",
            "textColor": "#000000"
        },
        {
            "id": "how-does-the-internet-work",
            "label": "How does the internet work?",
            "x": 0,
            "y": 45,
            "width": 180,
            "height": 40,
            "bgColor": "#ffdfb3",
            "textColor": "#000000"
        },
        {
            "id": "what-is-http",
            "label": "What is HTTP?",
            "x": 0,
            "y": 90,
            "width": 180,
            "height": 40,
            "bgColor": "#ffdfb3",
            "textColor": "#000000"
        },
        {
            "id": "what-is-domain-name",
            "label": "What is Domain Name?",
            "x": 0,
            "y": 135,
            "width": 180,
            "height": 40,
            "bgColor": "#ffdfb3",
            "textColor": "#000000"
        },
        {
            "id": "what-is-hosting",
            "label": "What is hosting?",
            "x": 0,
            "y": 180,
            "width": 180,
            "height": 40,
            "bgColor": "#ffdfb3",
            "textColor": "#000000"
        },
        {
            "id": "dns-and-how-it-works",
            "label": "DNS and how it works?",
            "x": 0,
            "y": 225,
            "width": 180,
            "height": 40,
            "bgColor": "#ffdfb3",
            "textColor": "#000000"
        },
        {
            "id": "browsers-and-how-they-work",
            "label": "Browsers and how they work?",
            "x": 0,
            "y": 270,
            "width": 180,
            "height": 40,
            "bgColor": "#ffdfb3",
            "textColor": "#000000"
        },
        {
            "id": "html",
            "label": "HTML",
            "x": 0,
            "y": 335,
            "width": 240,
            "height": 40,
            "bgColor": "#ffee55",
            "textColor": "#000000"
        },
        {
            "id": "learn-the-basics",
            "label": "Learn the Basics",
            "x": 0,
            "y": 380,
            "width": 180,
            "height": 40,
            "bgColor": "#ffdfb3",
            "textColor": "#000000"
        },
        {
            "id": "writing-semantic-html",
            "label": "Writing Semantic HTML",
            "x": 0,
            "y": 425,
            "width": 180,
            "height": 40,
            "bgColor": "#ffdfb3",
            "textColor": "#000000"
        },
        {
            "id": "forms-and-validations",
            "label": "Forms and Validations",
            "x": 0,
            "y": 470,
            "width": 180,
            "height": 40,
            "bgColor": "#ffdfb3",
            "textColor": "#000000"
        },
        {
            "id": "accessibility",
            "label": "Accessibility",
            "x": 0,
            "y": 515,
            "width": 180,
            "height": 40,
            "bgColor": "#ffdfb3",
            "textColor": "#000000"
        },
        {
            "id": "seo-basics",
            "label": "SEO Basics",
            "x": 0,
            "y": 560,
            "width": 180,
            "height": 40,
            "bgColor": "#ffdfb3",
            "textColor": "#000000"
        },
        {
            "id": "css",
            "label": "CSS",
            "x": 0,
            "y": 625,
            "width": 240,
            "height": 40,
            "bgColor": "#ffee55",
            "textColor": "#000000"
        },
        {
            "id": "css-learn-the-basics",
            "label": "Learn the Basics",
            "x": 0,
            "y": 670,
            "width": 180,
            "height": 40,
            "bgColor": "#ffdfb3",
            "textColor": "#000000"
        },
        {
            "id": "making-layouts",
            "label": "Making Layouts",
            "x": 0,
            "y": 715,
            "width": 180,
            "height": 40,
            "bgColor": "#ffdfb3",
            "textColor": "#000000"
        },
        {
            "id": "responsive-design",
            "label": "Responsive Design",
            "x": 0,
            "y": 760,
            "width": 180,
            "height": 40,
            "bgColor": "#ffdfb3",
            "textColor": "#000000"
        },
        {
            "id": "css-architecture",
            "label": "CSS Architecture",
            "x": 0,
            "y": 805,
            "width": 180,
            "height": 40,
            "bgColor": "#ffdfb3",
            "textColor": "#000000"
        },
        {
            "id": "bem",
            "label": "BEM",
            "x": 0,
            "y": 850,
            "width": 180,
            "height": 40,
            "bgColor": "#ffdfb3",
            "textColor": "#000000"
        },
        {
            "id": "css-preprocessors",
            "label": "CSS Preprocessors",
            "x": 0,
            "y": 895,
            "width": 180,
            "height": 40,
            "bgColor": "#ffdfb3",
            "textColor": "#000000"
        },
        {
            "id": "sass",
            "label": "Sass",
            "x": 0,
            "y": 940,
            "width": 180,
            "height": 40,
            "bgColor": "#ffdfb3",
            "textColor": "#000000"
        },
        {
            "id": "postcss",
            "label": "PostCSS",
            "x": 0,
            "y": 985,
            "width": 180,
            "height": 40,
            "bgColor": "#ffdfb3",
            "textColor": "#000000"
        },
        {
            "id": "javascript",
            "label": "JavaScript",
            "x": 0,
            "y": 1050,
            "width": 240,
            "height": 40,
            "bgColor": "#ffee55",
            "textColor": "#000000"
        },
        {
            "id": "learn-dom-manipulation",
            "label": "Learn DOM Manipulation",
            "x": 0,
            "y": 1095,
            "width": 180,
            "height": 40,
            "bgColor": "#ffdfb3",
            "textColor": "#000000"
        },
        {
            "id": "fetch-api-ajax-xhr",
            "label": "Fetch API / Ajax (XHR)",
            "x": 0,
            "y": 1140,
            "width": 180,
            "height": 40,
            "bgColor": "#ffdfb3",
            "textColor": "#000000"
        },
        {
            "id": "cors",
            "label": "CORS",
            "x": 0,
            "y": 1185,
            "width": 180,
            "height": 40,
            "bgColor": "#ffdfb3",
            "textColor": "#000000"
        },
        {
            "id": "https",
            "label": "HTTPS",
            "x": 0,
            "y": 1230,
            "width": 180,
            "height": 40,
            "bgColor": "#ffdfb3",
            "textColor": "#000000"
        },
        {
            "id": "version-control-systems",
            "label": "Version Control Systems",
            "x": 0,
            "y": 1295,
            "width": 240,
            "height": 40,
            "bgColor": "#ffee55",
            "textColor": "#000000"
        },
        {
            "id": "git",
            "label": "Git",
            "x": 0,
            "y": 1340,
            "width": 180,
            "height": 40,
            "bgColor": "#ffdfb3",
            "textColor": "#000000"
        },
        {
            "id": "vcs-hosting",
            "label": "VCS Hosting",
            "x": 0,
            "y": 1405,
            "width": 240,
            "height": 40,
            "bgColor": "#ffee55",
            "textColor": "#000000"
        },
        {
            "id": "github",
            "label": "GitHub",
            "x": 0,
            "y": 1450,
            "width": 180,
            "height": 40,
            "bgColor": "#ffdfb3",
            "textColor": "#000000"
        },
        {
            "id": "gitlab",
            "label": "GitLab",
            "x": 0,
            "y": 1495,
            "width": 180,
            "height": 40,
            "bgColor": "#ffdfb3",
            "textColor": "#000000"
        },
        {
            "id": "bitbucket",
            "label": "Bitbucket",
            "x": 0,
            "y": 1540,
            "width": 180,
            "height": 40,
            "bgColor": "#ffdfb3",
            "textColor": "#000000"
        },
        {
            "id": "package-managers",
            "label": "Package Managers",
            "x": 0,
            "y": 1605,
            "width": 240,
            "height": 40,
            "bgColor": "#ffee55",
            "textColor": "#000000"
        },
        {
            "id": "npm",
            "label": "npm",
            "x": 0,
            "y": 1650,
            "width": 180,
            "height": 40,
            "bgColor": "#ffdfb3",
            "textColor": "#000000"
        },
        {
            "id": "pnpm",
            "label": "pnpm",
            "x": 0,
            "y": 1695,
            "width": 180,
            "height": 40,
            "bgColor": "#ffdfb3",
            "textColor": "#000000"
        },
        {
            "id": "yarn",
            "label": "yarn",
            "x": 0,
            "y": 1740,
            "width": 180,
            "height": 40,
            "bgColor": "#ffdfb3",
            "textColor": "#000000"
        },
        {
            "id": "pick-a-framework",
            "label": "Pick a Framework",
            "x": 0,
            "y": 1805,
            "width": 240,
            "height": 40,
            "bgColor": "#ffee55",
            "textColor": "#000000"
        },
        {
            "id": "react",
            "label": "React",
            "x": 0,
            "y": 1850,
            "width": 180,
            "height": 40,
            "bgColor": "#ffdfb3",
            "textColor": "#000000"
        },
        {
            "id": "vue-js",
            "label": "Vue.js",
            "x": 0,
            "y": 1895,
            "width": 180,
            "height": 40,
            "bgColor": "#ffdfb3",
            "textColor": "#000000"
        },
        {
            "id": "angular",
            "label": "Angular",
            "x": 0,
            "y": 1940,
            "width": 180,
            "height": 40,
            "bgColor": "#ffdfb3",
            "textColor": "#000000"
        },
        {
            "id": "svelte",
            "label": "Svelte",
            "x": 0,
            "y": 1985,
            "width": 180,
            "height": 40,
            "bgColor": "#ffdfb3",
            "textColor": "#000000"
        },
        {
            "id": "solid-js",
            "label": "Solid JS",
            "x": 0,
            "y": 2030,
            "width": 180,
            "height": 40,
            "bgColor": "#ffdfb3",
            "textColor": "#000000"
        },
        {
            "id": "qwik",
            "label": "Qwik",
            "x": 0,
            "y": 2075,
            "width": 180,
            "height": 40,
            "bgColor": "#ffdfb3",
            "textColor": "#000000"
        },
        {
            "id": "writing-css",
            "label": "Writing CSS",
            "x": 0,
            "y": 2140,
            "width": 240,
            "height": 40,
            "bgColor": "#ffee55",
            "textColor": "#000000"
        },
        {
            "id": "tailwind",
            "label": "Tailwind",
            "x": 0,
            "y": 2185,
            "width": 180,
            "height": 40,
            "bgColor": "#ffdfb3",
            "textColor": "#000000"
        },
        {
            "id": "css-modules",
            "label": "CSS Modules",
            "x": 0,
            "y": 2230,
            "width": 180,
            "height": 40,
            "bgColor": "#ffdfb3",
            "textColor": "#000000"
        },
        {
            "id": "styled-components",
            "label": "Styled Components",
            "x": 0,
            "y": 2275,
            "width": 180,
            "height": 40,
            "bgColor": "#ffdfb3",
            "textColor": "#000000"
        },
        {
            "id": "build-tools",
            "label": "Build Tools",
            "x": 0,
            "y": 2340,
            "width": 240,
            "height": 40,
            "bgColor": "#ffee55",
            "textColor": "#000000"
        },
        {
            "id": "vite",
            "label": "Vite",
            "x": 0,
            "y": 2385,
            "width": 180,
            "height": 40,
            "bgColor": "#ffdfb3",
            "textColor": "#000000"
        },
        {
            "id": "webpack",
            "label": "Webpack",
            "x": 0,
            "y": 2430,
            "width": 180,
            "height": 40,
            "bgColor": "#ffdfb3",
            "textColor": "#000000"
        },
        {
            "id": "rollup",
            "label": "Rollup",
            "x": 0,
            "y": 2475,
            "width": 180,
            "height": 40,
            "bgColor": "#ffdfb3",
            "textColor": "#000000"
        },
        {
            "id": "parcel",
            "label": "Parcel",
            "x": 0,
            "y": 2520,
            "width": 180,
            "height": 40,
            "bgColor": "#ffdfb3",
            "textColor": "#000000"
        },
        {
            "id": "esbuild",
            "label": "esbuild",
            "x": 0,
            "y": 2565,
            "width": 180,
            "height": 40,
            "bgColor": "#ffdfb3",
            "textColor": "#000000"
        },
        {
            "id": "swc",
            "label": "SWC",
            "x": 0,
            "y": 2610,
            "width": 180,
            "height": 40,
            "bgColor": "#ffdfb3",
            "textColor": "#000000"
        },
        {
            "id": "linters-and-formatters",
            "label": "Linters and Formatters",
            "x": 0,
            "y": 2675,
            "width": 240,
            "height": 40,
            "bgColor": "#ffee55",
            "textColor": "#000000"
        },
        {
            "id": "prettier",
            "label": "Prettier",
            "x": 0,
            "y": 2720,
            "width": 180,
            "height": 40,
            "bgColor": "#ffdfb3",
            "textColor": "#000000"
        },
        {
            "id": "eslint",
            "label": "ESLint",
            "x": 0,
            "y": 2765,
            "width": 180,
            "height": 40,
            "bgColor": "#ffdfb3",
            "textColor": "#000000"
        },
        {
            "id": "testing",
            "label": "Testing",
            "x": 0,
            "y": 2830,
            "width": 240,
            "height": 40,
            "bgColor": "#ffee55",
            "textColor": "#000000"
        },
        {
            "id": "vitest",
            "label": "Vitest",
            "x": 0,
            "y": 2875,
            "width": 180,
            "height": 40,
            "bgColor": "#ffdfb3",
            "textColor": "#000000"
        },
        {
            "id": "jest",
            "label": "Jest",
            "x": 0,
            "y": 2920,
            "width": 180,
            "height": 40,
            "bgColor": "#ffdfb3",
            "textColor": "#000000"
        },
        {
            "id": "playwright",
            "label": "Playwright",
            "x": 0,
            "y": 2965,
            "width": 180,
            "height": 40,
            "bgColor": "#ffdfb3",
            "textColor": "#000000"
        },
        {
            "id": "cypress",
            "label": "Cypress",
            "x": 0,
            "y": 3010,
            "width": 180,
            "height": 40,
            "bgColor": "#ffdfb3",
            "textColor": "#000000"
        },
        {
            "id": "type-checkers",
            "label": "Type Checkers",
            "x": 0,
            "y": 3075,
            "width": 240,
            "height": 40,
            "bgColor": "#ffee55",
            "textColor": "#000000"
        },
        {
            "id": "typescript",
            "label": "TypeScript",
            "x": 0,
            "y": 3120,
            "width": 180,
            "height": 40,
            "bgColor": "#ffdfb3",
            "textColor": "#000000"
        },
        {
            "id": "web-security-basics",
            "label": "Web Security Basics",
            "x": 0,
            "y": 3185,
            "width": 240,
            "height": 40,
            "bgColor": "#ffee55",
            "textColor": "#000000"
        },
        {
            "id": "owasp-security-risks",
            "label": "OWASP Security Risks",
            "x": 0,
            "y": 3230,
            "width": 180,
            "height": 40,
            "bgColor": "#ffdfb3",
            "textColor": "#000000"
        },
        {
            "id": "content-security-policy",
            "label": "Content Security Policy",
            "x": 0,
            "y": 3275,
            "width": 180,
            "height": 40,
            "bgColor": "#ffdfb3",
            "textColor": "#000000"
        },
        {
            "id": "authentication-strategies",
            "label": "Authentication Strategies",
            "x": 0,
            "y": 3340,
            "width": 240,
            "height": 40,
            "bgColor": "#ffee55",
            "textColor": "#000000"
        },
        {
            "id": "jwt",
            "label": "JWT",
            "x": 0,
            "y": 3385,
            "width": 180,
            "height": 40,
            "bgColor": "#ffdfb3",
            "textColor": "#000000"
        },
        {
            "id": "oauth",
            "label": "OAuth",
            "x": 0,
            "y": 3430,
            "width": 180,
            "height": 40,
            "bgColor": "#ffdfb3",
            "textColor": "#000000"
        },
        {
            "id": "sso",
            "label": "SSO",
            "x": 0,
            "y": 3475,
            "width": 180,
            "height": 40,
            "bgColor": "#ffdfb3",
            "textColor": "#000000"
        },
        {
            "id": "basic-auth",
            "label": "Basic Auth",
            "x": 0,
            "y": 3520,
            "width": 180,
            "height": 40,
            "bgColor": "#ffdfb3",
            "textColor": "#000000"
        },
        {
            "id": "session-auth",
            "label": "Session Auth",
            "x": 0,
            "y": 3565,
            "width": 180,
            "height": 40,
            "bgColor": "#ffdfb3",
            "textColor": "#000000"
        },
        {
            "id": "web-components",
            "label": "Web Components",
            "x": 0,
            "y": 3630,
            "width": 240,
            "height": 40,
            "bgColor": "#ffee55",
            "textColor": "#000000"
        },
        {
            "id": "html-templates",
            "label": "HTML Templates",
            "x": 0,
            "y": 3675,
            "width": 180,
            "height": 40,
            "bgColor": "#ffdfb3",
            "textColor": "#000000"
        },
        {
            "id": "custom-elements",
            "label": "Custom Elements",
            "x": 0,
            "y": 3720,
            "width": 180,
            "height": 40,
            "bgColor": "#ffdfb3",
            "textColor": "#000000"
        },
        {
            "id": "shadow-dom",
            "label": "Shadow DOM",
            "x": 0,
            "y": 3765,
            "width": 180,
            "height": 40,
            "bgColor": "#ffdfb3",
            "textColor": "#000000"
        },
        {
            "id": "ssr",
            "label": "SSR",
            "x": 0,
            "y": 3830,
            "width": 240,
            "height": 40,
            "bgColor": "#ffee55",
            "textColor": "#000000"
        },
        {
            "id": "next-js",
            "label": "Next.js",
            "x": 0,
            "y": 3875,
            "width": 180,
            "height": 40,
            "bgColor": "#ffdfb3",
            "textColor": "#000000"
        },
        {
            "id": "nuxt-js",
            "label": "Nuxt.js",
            "x": 0,
            "y": 3920,
            "width": 180,
            "height": 40,
            "bgColor": "#ffdfb3",
            "textColor": "#000000"
        },
        {
            "id": "svelte-kit",
            "label": "Svelte Kit",
            "x": 0,
            "y": 3965,
            "width": 180,
            "height": 40,
            "bgColor": "#ffdfb3",
            "textColor": "#000000"
        },
        {
            "id": "astro",
            "label": "Astro",
            "x": 0,
            "y": 4010,
            "width": 180,
            "height": 40,
            "bgColor": "#ffdfb3",
            "textColor": "#000000"
        },
        {
            "id": "graphql",
            "label": "GraphQL",
            "x": 0,
            "y": 4075,
            "width": 240,
            "height": 40,
            "bgColor": "#ffee55",
            "textColor": "#000000"
        },
        {
            "id": "apollo",
            "label": "Apollo",
            "x": 0,
            "y": 4120,
            "width": 180,
            "height": 40,
            "bgColor": "#ffdfb3",
            "textColor": "#000000"
        },
        {
            "id": "relay-modern",
            "label": "Relay Modern",
            "x": 0,
            "y": 4165,
            "width": 180,
            "height": 40,
            "bgColor": "#ffdfb3",
            "textColor": "#000000"
        },
        {
            "id": "static-site-generators",
            "label": "Static Site Generators",
            "x": 0,
            "y": 4230,
            "width": 240,
            "height": 40,
            "bgColor": "#ffee55",
            "textColor": "#000000"
        },
        {
            "id": "eleventy",
            "label": "Eleventy",
            "x": 0,
            "y": 4275,
            "width": 180,
            "height": 40,
            "bgColor": "#ffdfb3",
            "textColor": "#000000"
        },
        {
            "id": "vuepress",
            "label": "Vuepress",
            "x": 0,
            "y": 4320,
            "width": 180,
            "height": 40,
            "bgColor": "#ffdfb3",
            "textColor": "#000000"
        },
        {
            "id": "static-site-generators-astro",
            "label": "Astro",
            "x": 0,
            "y": 4365,
            "width": 180,
            "height": 40,
            "bgColor": "#ffdfb3",
            "textColor": "#000000"
        },
        {
            "id": "mobile-apps",
            "label": "Mobile Apps",
            "x": 0,
            "y": 4430,
            "width": 240,
            "height": 40,
            "bgColor": "#ffee55",
            "textColor": "#000000"
        },
        {
            "id": "react-native",
            "label": "React Native",
            "x": 0,
            "y": 4475,
            "width": 180,
            "height": 40,
            "bgColor": "#ffdfb3",
            "textColor": "#000000"
        },
        {
            "id": "flutter",
            "label": "Flutter",
            "x": 0,
            "y": 4520,
            "width": 180,
            "height": 40,
            "bgColor": "#ffdfb3",
            "textColor": "#000000"
        },
        {
            "id": "ionic",
            "label": "Ionic",
            "x": 0,
            "y": 4565,
            "width": 180,
            "height": 40,
            "bgColor": "#ffdfb3",
            "textColor": "#000000"
        },
        {
            "id": "desktop-apps",
            "label": "Desktop Apps",
            "x": 0,
            "y": 4630,
            "width": 240,
            "height": 40,
            "bgColor": "#ffee55",
            "textColor": "#000000"
        },
        {
            "id": "electron",
            "label": "Electron",
            "x": 0,
            "y": 4675,
            "width": 180,
            "height": 40,
            "bgColor": "#ffdfb3",
            "textColor": "#000000"
        },
        {
            "id": "tauri",
            "label": "Tauri",
            "x": 0,
            "y": 4720,
            "width": 180,
            "height": 40,
            "bgColor": "#ffdfb3",
            "textColor": "#000000"
        },
        {
            "id": "desktop-apps-flutter",
            "label": "Flutter",
            "x": 0,
            "y": 4765,
            "width": 180,
            "height": 40,
            "bgColor": "#ffdfb3",
            "textColor": "#000000"
        },
        {
            "id": "performance-best-practices",
            "label": "Performance Best Practices",
            "x": 0,
            "y": 4830,
            "width": 240,
            "height": 40,
            "bgColor": "#ffee55",
            "textColor": "#000000"
        },
        {
            "id": "prpl-pattern",
            "label": "PRPL Pattern",
            "x": 0,
            "y": 4875,
            "width": 180,
            "height": 40,
            "bgColor": "#ffdfb3",
            "textColor": "#000000"
        },
        {
            "id": "rail-model",
            "label": "RAIL Model",
            "x": 0,
            "y": 4920,
            "width": 180,
            "height": 40,
            "bgColor": "#ffdfb3",
            "textColor": "#000000"
        },
        {
            "id": "performance-metrics",
            "label": "Performance Metrics",
            "x": 0,
            "y": 4965,
            "width": 180,
            "height": 40,
            "bgColor": "#ffdfb3",
            "textColor": "#000000"
        },
        {
            "id": "using-lighthouse",
            "label": "Using Lighthouse",
            "x": 0,
            "y": 5010,
            "width": 180,
            "height": 40,
            "bgColor": "#ffdfb3",
            "textColor": "#000000"
        },
        {
            "id": "using-devtools",
            "label": "Using DevTools",
            "x": 0,
            "y": 5055,
            "width": 180,
            "height": 40,
            "bgColor": "#ffdfb3",
            "textColor": "#000000"
        },
        {
            "id": "browser-apis",
            "label": "Browser APIs",
            "x": 0,
            "y": 5120,
            "width": 240,
            "height": 40,
            "bgColor": "#ffee55",
            "textColor": "#000000"
        },
        {
            "id": "web-sockets",
            "label": "Web Sockets",
            "x": 0,
            "y": 5165,
            "width": 180,
            "height": 40,
            "bgColor": "#ffdfb3",
            "textColor": "#000000"
        },
        {
            "id": "server-sent-events",
            "label": "Server Sent Events",
            "x": 0,
            "y": 5210,
            "width": 180,
            "height": 40,
            "bgColor": "#ffdfb3",
            "textColor": "#000000"
        },
        {
            "id": "service-workers",
            "label": "Service Workers",
            "x": 0,
            "y": 5255,
            "width": 180,
            "height": 40,
            "bgColor": "#ffdfb3",
            "textColor": "#000000"
        },
        {
            "id": "storage",
            "label": "Storage",
            "x": 0,
            "y": 5300,
            "width": 180,
            "height": 40,
            "bgColor": "#ffdfb3",
            "textColor": "#000000"
        },
        {
            "id": "location",
            "label": "Location",
            "x": 0,
            "y": 5345,
            "width": 180,
            "height": 40,
            "bgColor": "#ffdfb3",
            "textColor": "#000000"
        },
        {
            "id": "notifications",
            "label": "Notifications",
            "x": 0,
            "y": 5390,
            "width": 180,
            "height": 40,
            "bgColor": "#ffdfb3",
            "textColor": "#000000"
        },
        {
            "id": "device-orientation",
            "label": "Device Orientation",
            "x": 0,
            "y": 5435,
            "width": 180,
            "height": 40,
            "bgColor": "#ffdfb3",
            "textColor": "#000000"
        },
        {
            "id": "payments",
            "label": "Payments",
            "x": 0,
            "y": 5480,
            "width": 180,
            "height": 40,
            "bgColor": "#ffdfb3",
            "textColor": "#000000"
        },
        {
            "id": "credentials",
            "label": "Credentials",
            "x": 0,
            "y": 5525,
            "width": 180,
            "height": 40,
            "bgColor": "#ffdfb3",
            "textColor": "#000000"
        },
        {
            "id": "pwas",
            "label": "PWAs",
            "x": 0,
            "y": 5590,
            "width": 240,
            "height": 40,
            "bgColor": "#ffee55",
            "textColor": "#000000"
        },
        {
            "id": "progressive-web-apps",
            "label": "Progressive Web Apps",
            "x": 0,
            "y": 5635,
            "width": 180,
            "height": 40,
            "bgColor": "#ffdfb3",
            "textColor": "#000000"
        }
    ],
    "edges": [
        {
            "id": "e-internet-how-does-the-internet-work",
            "source": "internet",
            "target": "how-does-the-internet-work"
        },
        {
            "id": "e-internet-what-is-http",
            "source": "internet",
            "target": "what-is-http"
        },
        {
            "id": "e-internet-what-is-domain-name",
            "source": "internet",
            "target": "what-is-domain-name"
        },
        {
            "id": "e-internet-what-is-hosting",
            "source": "internet",
            "target": "what-is-hosting"
        },
        {
            "id": "e-internet-dns-and-how-it-works",
            "source": "internet",
            "target": "dns-and-how-it-works"
        },
        {
            "id": "e-internet-browsers-and-how-they-work",
            "source": "internet",
            "target": "browsers-and-how-they-work"
        },
        {
            "id": "e-internet-html",
            "source": "internet",
            "target": "html"
        },
        {
            "id": "e-html-learn-the-basics",
            "source": "html",
            "target": "learn-the-basics"
        },
        {
            "id": "e-html-writing-semantic-html",
            "source": "html",
            "target": "writing-semantic-html"
        },
        {
            "id": "e-html-forms-and-validations",
            "source": "html",
            "target": "forms-and-validations"
        },
        {
            "id": "e-html-accessibility",
            "source": "html",
            "target": "accessibility"
        },
        {
            "id": "e-html-seo-basics",
            "source": "html",
            "target": "seo-basics"
        },
        {
            "id": "e-html-css",
            "source": "html",
            "target": "css"
        },
        {
            "id": "e-css-css-learn-the-basics",
            "source": "css",
            "target": "css-learn-the-basics"
        },
        {
            "id": "e-css-making-layouts",
            "source": "css",
            "target": "making-layouts"
        },
        {
            "id": "e-css-responsive-design",
            "source": "css",
            "target": "responsive-design"
        },
        {
            "id": "e-css-css-architecture",
            "source": "css",
            "target": "css-architecture"
        },
        {
            "id": "e-css-bem",
            "source": "css",
            "target": "bem"
        },
        {
            "id": "e-css-css-preprocessors",
            "source": "css",
            "target": "css-preprocessors"
        },
        {
            "id": "e-css-sass",
            "source": "css",
            "target": "sass"
        },
        {
            "id": "e-css-postcss",
            "source": "css",
            "target": "postcss"
        },
        {
            "id": "e-css-javascript",
            "source": "css",
            "target": "javascript"
        },
        {
            "id": "e-javascript-learn-dom-manipulation",
            "source": "javascript",
            "target": "learn-dom-manipulation"
        },
        {
            "id": "e-javascript-fetch-api-ajax-xhr",
            "source": "javascript",
            "target": "fetch-api-ajax-xhr"
        },
        {
            "id": "e-javascript-cors",
            "source": "javascript",
            "target": "cors"
        },
        {
            "id": "e-javascript-https",
            "source": "javascript",
            "target": "https"
        },
        {
            "id": "e-javascript-version-control-systems",
            "source": "javascript",
            "target": "version-control-systems"
        },
        {
            "id": "e-version-control-systems-git",
            "source": "version-control-systems",
            "target": "git"
        },
        {
            "id": "e-version-control-systems-vcs-hosting",
            "source": "version-control-systems",
            "target": "vcs-hosting"
        },
        {
            "id": "e-vcs-hosting-github",
            "source": "vcs-hosting",
            "target": "github"
        },
        {
            "id": "e-vcs-hosting-gitlab",
            "source": "vcs-hosting",
            "target": "gitlab"
        },
        {
            "id": "e-vcs-hosting-bitbucket",
            "source": "vcs-hosting",
            "target": "bitbucket"
        },
        {
            "id": "e-vcs-hosting-package-managers",
            "source": "vcs-hosting",
            "target": "package-managers"
        },
        {
            "id": "e-package-managers-npm",
            "source": "package-managers",
            "target": "npm"
        },
        {
            "id": "e-package-managers-pnpm",
            "source": "package-managers",
            "target": "pnpm"
        },
        {
            "id": "e-package-managers-yarn",
            "source": "package-managers",
            "target": "yarn"
        },
        {
            "id": "e-package-managers-pick-a-framework",
            "source": "package-managers",
            "target": "pick-a-framework"
        },
        {
            "id": "e-pick-a-framework-react",
            "source": "pick-a-framework",
            "target": "react"
        },
        {
            "id": "e-pick-a-framework-vue-js",
            "source": "pick-a-framework",
            "target": "vue-js"
        },
        {
            "id": "e-pick-a-framework-angular",
            "source": "pick-a-framework",
            "target": "angular"
        },
        {
            "id": "e-pick-a-framework-svelte",
            "source": "pick-a-framework",
            "target": "svelte"
        },
        {
            "id": "e-pick-a-framework-solid-js",
            "source": "pick-a-framework",
            "target": "solid-js"
        },
        {
            "id": "e-pick-a-framework-qwik",
            "source": "pick-a-framework",
            "target": "qwik"
        },
        {
            "id": "e-pick-a-framework-writing-css",
            "source": "pick-a-framework",
            "target": "writing-css"
        },
        {
            "id": "e-writing-css-tailwind",
            "source": "writing-css",
            "target": "tailwind"
        },
        {
            "id": "e-writing-css-css-modules",
            "source": "writing-css",
            "target": "css-modules"
        },
        {
            "id": "e-writing-css-styled-components",
            "source": "writing-css",
            "target": "styled-components"
        },
        {
            "id": "e-writing-css-build-tools",
            "source": "writing-css",
            "target": "build-tools"
        },
        {
            "id": "e-build-tools-vite",
            "source": "build-tools",
            "target": "vite"
        },
        {
            "id": "e-build-tools-webpack",
            "source": "build-tools",
            "target": "webpack"
        },
        {
            "id": "e-build-tools-rollup",
            "source": "build-tools",
            "target": "rollup"
        },
        {
            "id": "e-build-tools-parcel",
            "source": "build-tools",
            "target": "parcel"
        },
        {
            "id": "e-build-tools-esbuild",
            "source": "build-tools",
            "target": "esbuild"
        },
        {
            "id": "e-build-tools-swc",
            "source": "build-tools",
            "target": "swc"
        },
        {
            "id": "e-build-tools-linters-and-formatters",
            "source": "build-tools",
            "target": "linters-and-formatters"
        },
        {
            "id": "e-linters-and-formatters-prettier",
            "source": "linters-and-formatters",
            "target": "prettier"
        },
        {
            "id": "e-linters-and-formatters-eslint",
            "source": "linters-and-formatters",
            "target": "eslint"
        },
        {
            "id": "e-linters-and-formatters-testing",
            "source": "linters-and-formatters",
            "target": "testing"
        },
        {
            "id": "e-testing-vitest",
            "source": "testing",
            "target": "vitest"
        },
        {
            "id": "e-testing-jest",
            "source": "testing",
            "target": "jest"
        },
        {
            "id": "e-testing-playwright",
            "source": "testing",
            "target": "playwright"
        },
        {
            "id": "e-testing-cypress",
            "source": "testing",
            "target": "cypress"
        },
        {
            "id": "e-testing-type-checkers",
            "source": "testing",
            "target": "type-checkers"
        },
        {
            "id": "e-type-checkers-typescript",
            "source": "type-checkers",
            "target": "typescript"
        },
        {
            "id": "e-type-checkers-web-security-basics",
            "source": "type-checkers",
            "target": "web-security-basics"
        },
        {
            "id": "e-web-security-basics-owasp-security-risks",
            "source": "web-security-basics",
            "target": "owasp-security-risks"
        },
        {
            "id": "e-web-security-basics-content-security-policy",
            "source": "web-security-basics",
            "target": "content-security-policy"
        },
        {
            "id": "e-web-security-basics-authentication-strategies",
            "source": "web-security-basics",
            "target": "authentication-strategies"
        },
        {
            "id": "e-authentication-strategies-jwt",
            "source": "authentication-strategies",
            "target": "jwt"
        },
        {
            "id": "e-authentication-strategies-oauth",
            "source": "authentication-strategies",
            "target": "oauth"
        },
        {
            "id": "e-authentication-strategies-sso",
            "source": "authentication-strategies",
            "target": "sso"
        },
        {
            "id": "e-authentication-strategies-basic-auth",
            "source": "authentication-strategies",
            "target": "basic-auth"
        },
        {
            "id": "e-authentication-strategies-session-auth",
            "source": "authentication-strategies",
            "target": "session-auth"
        },
        {
            "id": "e-authentication-strategies-web-components",
            "source": "authentication-strategies",
            "target": "web-components"
        },
        {
            "id": "e-web-components-html-templates",
            "source": "web-components",
            "target": "html-templates"
        },
        {
            "id": "e-web-components-custom-elements",
            "source": "web-components",
            "target": "custom-elements"
        },
        {
            "id": "e-web-components-shadow-dom",
            "source": "web-components",
            "target": "shadow-dom"
        },
        {
            "id": "e-web-components-ssr",
            "source": "web-components",
            "target": "ssr"
        },
        {
            "id": "e-ssr-next-js",
            "source": "ssr",
            "target": "next-js"
        },
        {
            "id": "e-ssr-nuxt-js",
            "source": "ssr",
            "target": "nuxt-js"
        },
        {
            "id": "e-ssr-svelte-kit",
            "source": "ssr",
            "target": "svelte-kit"
        },
        {
            "id": "e-ssr-astro",
            "source": "ssr",
            "target": "astro"
        },
        {
            "id": "e-ssr-graphql",
            "source": "ssr",
            "target": "graphql"
        },
        {
            "id": "e-graphql-apollo",
            "source": "graphql",
            "target": "apollo"
        },
        {
            "id": "e-graphql-relay-modern",
            "source": "graphql",
            "target": "relay-modern"
        },
        {
            "id": "e-graphql-static-site-generators",
            "source": "graphql",
            "target": "static-site-generators"
        },
        {
            "id": "e-static-site-generators-eleventy",
            "source": "static-site-generators",
            "target": "eleventy"
        },
        {
            "id": "e-static-site-generators-vuepress",
            "source": "static-site-generators",
            "target": "vuepress"
        },
        {
            "id": "e-static-site-generators-static-site-generators-astro",
            "source": "static-site-generators",
            "target": "static-site-generators-astro"
        },
        {
            "id": "e-static-site-generators-mobile-apps",
            "source": "static-site-generators",
            "target": "mobile-apps"
        },
        {
            "id": "e-mobile-apps-react-native",
            "source": "mobile-apps",
            "target": "react-native"
        },
        {
            "id": "e-mobile-apps-flutter",
            "source": "mobile-apps",
            "target": "flutter"
        },
        {
            "id": "e-mobile-apps-ionic",
            "source": "mobile-apps",
            "target": "ionic"
        },
        {
            "id": "e-mobile-apps-desktop-apps",
            "source": "mobile-apps",
            "target": "desktop-apps"
        },
        {
            "id": "e-desktop-apps-electron",
            "source": "desktop-apps",
            "target": "electron"
        },
        {
            "id": "e-desktop-apps-tauri",
            "source": "desktop-apps",
            "target": "tauri"
        },
        {
            "id": "e-desktop-apps-desktop-apps-flutter",
            "source": "desktop-apps",
            "target": "desktop-apps-flutter"
        },
        {
            "id": "e-desktop-apps-performance-best-practices",
            "source": "desktop-apps",
            "target": "performance-best-practices"
        },
        {
            "id": "e-performance-best-practices-prpl-pattern",
            "source": "performance-best-practices",
            "target": "prpl-pattern"
        },
        {
            "id": "e-performance-best-practices-rail-model",
            "source": "performance-best-practices",
            "target": "rail-model"
        },
        {
            "id": "e-performance-best-practices-performance-metrics",
            "source": "performance-best-practices",
            "target": "performance-metrics"
        },
        {
            "id": "e-performance-best-practices-using-lighthouse",
            "source": "performance-best-practices",
            "target": "using-lighthouse"
        },
        {
            "id": "e-performance-best-practices-using-devtools",
            "source": "performance-best-practices",
            "target": "using-devtools"
        },
        {
            "id": "e-performance-best-practices-browser-apis",
            "source": "performance-best-practices",
            "target": "browser-apis"
        },
        {
            "id": "e-browser-apis-web-sockets",
            "source": "browser-apis",
            "target": "web-sockets"
        },
        {
            "id": "e-browser-apis-server-sent-events",
            "source": "browser-apis",
            "target": "server-sent-events"
        },
        {
            "id": "e-browser-apis-service-workers",
            "source": "browser-apis",
            "target": "service-workers"
        },
        {
            "id": "e-browser-apis-storage",
            "source": "browser-apis",
            "target": "storage"
        },
        {
            "id": "e-browser-apis-location",
            "source": "browser-apis",
            "target": "location"
        },
        {
            "id": "e-browser-apis-notifications",
            "source": "browser-apis",
            "target": "notifications"
        },
        {
            "id": "e-browser-apis-device-orientation",
            "source": "browser-apis",
            "target": "device-orientation"
        },
        {
            "id": "e-browser-apis-payments",
            "source": "browser-apis",
            "target": "payments"
        },
        {
            "id": "e-browser-apis-credentials",
            "source": "browser-apis",
            "target": "credentials"
        },
        {
            "id": "e-browser-apis-pwas",
            "source": "browser-apis",
            "target": "pwas"
        },
        {
            "id": "e-pwas-progressive-web-apps",
            "source": "pwas",
            "target": "progressive-web-apps"
        }
    ]
}